[
  {
    "type": "function",
    "name": "addAllowedVoter",
    "inputs": [
      {
        "name": "_pollId",
        "type": "string",
        "internalType": "string"
      },
      {
        "name": "_voters",
        "type": "address[]",
        "internalType": "address[]"
      }
    ],
    "outputs": [],
    "stateMutability": "nonpayable"
  },
  {
    "type": "function",
    "name": "allPolls",
    "inputs": [
      {
        "name": "",
        "type": "uint256",
        "internalType": "uint256"
      }
    ],
    "outputs": [
      {
        "name": "pollId",
        "type": "string",
        "internalType": "string"
      },
      {
        "name": "creator",
        "type": "address",
        "internalType": "address"
      },
      {
        "name": "question",
        "type": "string",
        "internalType": "string"
      },
      {
        "name": "visible",
        "type": "uint8",
        "internalType": "enum PollFactory.Visibility"
      },
      {
        "name": "startTime",
        "type": "uint256",
        "internalType": "uint256"
      },
      {
        "name": "endTime",
        "type": "uint256",
        "internalType": "uint256"
      },
      {
        "name": "isActive",
        "type": "bool",
        "internalType": "bool"
      },
      {
        "name": "totalVotes",
        "type": "uint256",
        "internalType": "uint256"
      }
    ],
    "stateMutability": "view"
  },
  {
    "type": "function",
    "name": "createPoll",
    "inputs": [
      {
        "name": "_pollId",
        "type": "string",
        "internalType": "string"
      },
      {
        "name": "_question",
        "type": "string",
        "internalType": "string"
      },
      {
        "name": "_options",
        "type": "string[]",
        "internalType": "string[]"
      },
      {
        "name": "_visible",
        "type": "uint8",
        "internalType": "enum PollFactory.Visibility"
      },
      {
        "name": "_startTime",
        "type": "uint256",
        "internalType": "uint256"
      },
      {
        "name": "_endTime",
        "type": "uint256",
        "internalType": "uint256"
      }
    ],
    "outputs": [],
    "stateMutability": "nonpayable"
  },
  {
    "type": "function",
    "name": "endPoll",
    "inputs": [
      {
        "name": "_pollId",
        "type": "string",
        "internalType": "string"
      }
    ],
    "outputs": [],
    "stateMutability": "nonpayable"
  },
  {
    "type": "function",
    "name": "getAllPublicPolls",
    "inputs": [
      {
        "name": "_user",
        "type": "address",
        "internalType": "address"
      }
    ],
    "outputs": [
      {
        "name": "",
        "type": "tuple[]",
        "internalType": "struct PollFactory.PollData[]",
        "components": [
          {
            "name": "pollId",
            "type": "string",
            "internalType": "string"
          },
          {
            "name": "creator",
            "type": "address",
            "internalType": "address"
          },
          {
            "name": "question",
            "type": "string",
            "internalType": "string"
          },
          {
            "name": "options",
            "type": "string[]",
            "internalType": "string[]"
          },
          {
            "name": "visible",
            "type": "uint8",
            "internalType": "enum PollFactory.Visibility"
          },
          {
            "name": "startTime",
            "type": "uint256",
            "internalType": "uint256"
          },
          {
            "name": "endTime",
            "type": "uint256",
            "internalType": "uint256"
          },
          {
            "name": "isActive",
            "type": "bool",
            "internalType": "bool"
          },
          {
            "name": "totalVotes",
            "type": "uint256",
            "internalType": "uint256"
          },
          {
            "name": "hasVoted",
            "type": "bool",
            "internalType": "bool"
          },
          {
            "name": "voteCounts",
            "type": "uint256[]",
            "internalType": "uint256[]"
          },
          {
            "name": "userVote",
            "type": "string",
            "internalType": "string"
          }
        ]
      }
    ],
    "stateMutability": "view"
  },
  {
    "type": "function",
    "name": "getMyCreatedPolls",
    "inputs": [
      {
        "name": "_user",
        "type": "address",
        "internalType": "address"
      }
    ],
    "outputs": [
      {
        "name": "",
        "type": "tuple[]",
        "internalType": "struct PollFactory.PollData[]",
        "components": [
          {
            "name": "pollId",
            "type": "string",
            "internalType": "string"
          },
          {
            "name": "creator",
            "type": "address",
            "internalType": "address"
          },
          {
            "name": "question",
            "type": "string",
            "internalType": "string"
          },
          {
            "name": "options",
            "type": "string[]",
            "internalType": "string[]"
          },
          {
            "name": "visible",
            "type": "uint8",
            "internalType": "enum PollFactory.Visibility"
          },
          {
            "name": "startTime",
            "type": "uint256",
            "internalType": "uint256"
          },
          {
            "name": "endTime",
            "type": "uint256",
            "internalType": "uint256"
          },
          {
            "name": "isActive",
            "type": "bool",
            "internalType": "bool"
          },
          {
            "name": "totalVotes",
            "type": "uint256",
            "internalType": "uint256"
          },
          {
            "name": "hasVoted",
            "type": "bool",
            "internalType": "bool"
          },
          {
            "name": "voteCounts",
            "type": "uint256[]",
            "internalType": "uint256[]"
          },
          {
            "name": "userVote",
            "type": "string",
            "internalType": "string"
          }
        ]
      }
    ],
    "stateMutability": "view"
  },
  {
    "type": "function",
    "name": "getMyVotedPolls",
    "inputs": [
      {
        "name": "_user",
        "type": "address",
        "internalType": "address"
      }
    ],
    "outputs": [
      {
        "name": "",
        "type": "tuple[]",
        "internalType": "struct PollFactory.PollData[]",
        "components": [
          {
            "name": "pollId",
            "type": "string",
            "internalType": "string"
          },
          {
            "name": "creator",
            "type": "address",
            "internalType": "address"
          },
          {
            "name": "question",
            "type": "string",
            "internalType": "string"
          },
          {
            "name": "options",
            "type": "string[]",
            "internalType": "string[]"
          },
          {
            "name": "visible",
            "type": "uint8",
            "internalType": "enum PollFactory.Visibility"
          },
          {
            "name": "startTime",
            "type": "uint256",
            "internalType": "uint256"
          },
          {
            "name": "endTime",
            "type": "uint256",
            "internalType": "uint256"
          },
          {
            "name": "isActive",
            "type": "bool",
            "internalType": "bool"
          },
          {
            "name": "totalVotes",
            "type": "uint256",
            "internalType": "uint256"
          },
          {
            "name": "hasVoted",
            "type": "bool",
            "internalType": "bool"
          },
          {
            "name": "voteCounts",
            "type": "uint256[]",
            "internalType": "uint256[]"
          },
          {
            "name": "userVote",
            "type": "string",
            "internalType": "string"
          }
        ]
      }
    ],
    "stateMutability": "view"
  },
  {
    "type": "function",
    "name": "getPollById",
    "inputs": [
      {
        "name": "_pollId",
        "type": "string",
        "internalType": "string"
      },
      {
        "name": "_user",
        "type": "address",
        "internalType": "address"
      }
    ],
    "outputs": [
      {
        "name": "",
        "type": "tuple",
        "internalType": "struct PollFactory.PollData",
        "components": [
          {
            "name": "pollId",
            "type": "string",
            "internalType": "string"
          },
          {
            "name": "creator",
            "type": "address",
            "internalType": "address"
          },
          {
            "name": "question",
            "type": "string",
            "internalType": "string"
          },
          {
            "name": "options",
            "type": "string[]",
            "internalType": "string[]"
          },
          {
            "name": "visible",
            "type": "uint8",
            "internalType": "enum PollFactory.Visibility"
          },
          {
            "name": "startTime",
            "type": "uint256",
            "internalType": "uint256"
          },
          {
            "name": "endTime",
            "type": "uint256",
            "internalType": "uint256"
          },
          {
            "name": "isActive",
            "type": "bool",
            "internalType": "bool"
          },
          {
            "name": "totalVotes",
            "type": "uint256",
            "internalType": "uint256"
          },
          {
            "name": "hasVoted",
            "type": "bool",
            "internalType": "bool"
          },
          {
            "name": "voteCounts",
            "type": "uint256[]",
            "internalType": "uint256[]"
          },
          {
            "name": "userVote",
            "type": "string",
            "internalType": "string"
          }
        ]
      }
    ],
    "stateMutability": "view"
  },
  {
    "type": "function",
    "name": "getUserVote",
    "inputs": [
      {
        "name": "_pollId",
        "type": "string",
        "internalType": "string"
      },
      {
        "name": "_user",
        "type": "address",
        "internalType": "address"
      }
    ],
    "outputs": [
      {
        "name": "",
        "type": "string",
        "internalType": "string"
      }
    ],
    "stateMutability": "view"
  },
  {
    "type": "function",
    "name": "pollExists",
    "inputs": [
      {
        "name": "",
        "type": "string",
        "internalType": "string"
      }
    ],
    "outputs": [
      {
        "name": "",
        "type": "bool",
        "internalType": "bool"
      }
    ],
    "stateMutability": "view"
  },
  {
    "type": "function",
    "name": "pollIndex",
    "inputs": [
      {
        "name": "",
        "type": "string",
        "internalType": "string"
      }
    ],
    "outputs": [
      {
        "name": "",
        "type": "uint256",
        "internalType": "uint256"
      }
    ],
    "stateMutability": "view"
  },
  {
    "type": "function",
    "name": "userCreatedPolls",
    "inputs": [
      {
        "name": "",
        "type": "address",
        "internalType": "address"
      },
      {
        "name": "",
        "type": "uint256",
        "internalType": "uint256"
      }
    ],
    "outputs": [
      {
        "name": "",
        "type": "string",
        "internalType": "string"
      }
    ],
    "stateMutability": "view"
  },
  {
    "type": "function",
    "name": "userVotedPolls",
    "inputs": [
      {
        "name": "",
        "type": "address",
        "internalType": "address"
      },
      {
        "name": "",
        "type": "uint256",
        "internalType": "uint256"
      }
    ],
    "outputs": [
      {
        "name": "",
        "type": "string",
        "internalType": "string"
      }
    ],
    "stateMutability": "view"
  },
  {
    "type": "function",
    "name": "vote",
    "inputs": [
      {
        "name": "_pollId",
        "type": "string",
        "internalType": "string"
      },
      {
        "name": "_option",
        "type": "string",
        "internalType": "string"
      }
    ],
    "outputs": [],
    "stateMutability": "nonpayable"
  },
  {
    "type": "event",
    "name": "AllowedVotersAdded",
    "inputs": [
      {
        "name": "pollId",
        "type": "string",
        "indexed": true,
        "internalType": "string"
      },
      {
        "name": "voters",
        "type": "address[]",
        "indexed": false,
        "internalType": "address[]"
      }
    ],
    "anonymous": false
  },
  {
    "type": "event",
    "name": "PollCreated",
    "inputs": [
      {
        "name": "pollId",
        "type": "string",
        "indexed": true,
        "internalType": "string"
      },
      {
        "name": "creator",
        "type": "address",
        "indexed": true,
        "internalType": "address"
      },
      {
        "name": "visible",
        "type": "uint8",
        "indexed": false,
        "internalType": "enum PollFactory.Visibility"
      },
      {
        "name": "startTime",
        "type": "uint256",
        "indexed": false,
        "internalType": "uint256"
      },
      {
        "name": "endTime",
        "type": "uint256",
        "indexed": false,
        "internalType": "uint256"
      }
    ],
    "anonymous": false
  },
  {
    "type": "event",
    "name": "PollEnded",
    "inputs": [
      {
        "name": "pollId",
        "type": "string",
        "indexed": true,
        "internalType": "string"
      },
      {
        "name": "winningOption",
        "type": "string",
        "indexed": false,
        "internalType": "string"
      },
      {
        "name": "winningVotes",
        "type": "uint256",
        "indexed": false,
        "internalType": "uint256"
      }
    ],
    "anonymous": false
  },
  {
    "type": "event",
    "name": "VoteCasted",
    "inputs": [
      {
        "name": "pollId",
        "type": "string",
        "indexed": true,
        "internalType": "string"
      },
      {
        "name": "voter",
        "type": "address",
        "indexed": true,
        "internalType": "address"
      },
      {
        "name": "option",
        "type": "string",
        "indexed": false,
        "internalType": "string"
      }
    ],
    "anonymous": false
  }
]
